provisioner_installers_plugin/__init__.py
provisioner_installers_plugin/main.py
provisioner_installers_plugin/main_dev.py
provisioner_installers_plugin/main_fake.py
provisioner_installers_plugin/resources/__init__.py
provisioner_installers_plugin/resources/config.yaml
provisioner_installers_plugin/resources/version.txt
provisioner_installers_plugin/src/cli/__init__.py
provisioner_installers_plugin/src/cli/cli.py
provisioner_installers_plugin/src/cli/cli_test.py
provisioner_installers_plugin/src/config/domain/config.py
provisioner_installers_plugin/src/config/domain/config_fakes.py
provisioner_installers_plugin/src/installer/__init__.py
provisioner_installers_plugin/src/installer/cmd/__init__.py
provisioner_installers_plugin/src/installer/cmd/installer_cmd.py
provisioner_installers_plugin/src/installer/cmd/installer_cmd_test.py
provisioner_installers_plugin/src/installer/domain/command.py
provisioner_installers_plugin/src/installer/domain/dynamic_args.py
provisioner_installers_plugin/src/installer/domain/installable.py
provisioner_installers_plugin/src/installer/domain/source.py
provisioner_installers_plugin/src/installer/domain/source_test.py
provisioner_installers_plugin/src/installer/runner/__init__.py
provisioner_installers_plugin/src/installer/runner/installer_runner.py
provisioner_installers_plugin/src/installer/runner/installer_runner_test.py
provisioner_installers_plugin/src/installer/utilities.py
provisioner_installers_plugin/src/installer/versions.py
provisioner_installers_plugin/src/k3s/cli.py
provisioner_installers_plugin-0.1.6.dist-info/METADATA
provisioner_installers_plugin-0.1.6.dist-info/WHEEL
provisioner_installers_plugin-0.1.6.dist-info/entry_points.txt
provisioner_installers_plugin-0.1.6.dist-info/RECORD
