Metadata-Version: 2.1
Name: provisioner_installers_plugin
Version: 0.1.6
Summary: Python Installers Library
Author: Zachi Nachshon
Author-email: zachi.nachshon@gmail.com
Requires-Python: >=3.11,<4.0
Classifier: Programming Language :: Python :: 3
Classifier: Programming Language :: Python :: 3.11
Classifier: Programming Language :: Python :: 3.12
Classifier: Programming Language :: Python :: 3.13
Requires-Dist: provisioner-shared (>=0.1.11,<0.2.0)
